{
    "ID": "QuizModus",
    "layout": {
        "widget": "page",
        "children": [
            {
                "title": "QuizModus",
                "text": "Los gehts",
                "print-pointer": "0.txt",
                "widget": "button",
                "schema": {
                    "type": "object",
                    "properties": {
                        "Fachbereich": {
                            "widget": "select",
                            "options": "$all(\"postgres\", \"Fachbereich\").ID",
                            "style": {
                                "width": "700px"
                            } 
                        }
                    }
                }
            }
        ]
    }
}